{
    "intents": [
      {
        "tag": "greeting",
        "patterns": [
          "Hello",
          "Hi",
          "Hey",
          "What's up",
          "Howdy"
        ],
        "responses": [
          "Hello! How can I help you today?",
          "Hi there! What can I do for you?",
          "Hey! How can I assist you?",
          "What's up! How may I assist you?"
        ]
      },
      {
        "tag": "goodbye",
        "patterns": [
          "Bye",
          "See you later",
          "Goodbye",
          "See ya",
          "Later"
        ],
        "responses": [
          "Goodbye! Have a great day.",
          "See you later! Have a good one.",
          "Take care and have a good day.",
          "Bye! Have a great one."
        ]
      },
      {
        "tag": "thanks",
        "patterns": [
          "Thanks",
          "Thank you",
          "Appreciate it",
          "Thanks a lot",
          "Thank you so much"
        ],
        "responses": [
          "You're welcome! Is there anything else I can help you with?",
          "No problem! What else can I assist you with?",
          "Anytime! What can I do for you?",
          "Glad to help! What else can I assist you with?"
        ]
      },
      {
        "tag": "help",
        "patterns": [
          "Can you help?",
          "What should I type?",
          "Can you give suggestions on what to type?",
          "How can you assist me?",
          "I'm not sure what to ask, can you suggest something?",
          "I need some guidance on how to use this chatbot.",
          "What are some things I can ask you?",
          "What is the purpose of this chatbot?"
        ],
        "responses": [
          "I can help with telling the story based on the book 'The Hobbit' ",
          "I can help with detailing the location we are in, or any detail related to a character you want to learn. I'll do my best to provide you with good answers to your questions!",
          "I can tell you about details relating to characters and locations within the book 'The Hobbit' story. What are you interested in learning about?"
        ]
      }
    ]
  }
  